setup.py
django_file_repository.egg-info/PKG-INFO
django_file_repository.egg-info/SOURCES.txt
django_file_repository.egg-info/dependency_links.txt
django_file_repository.egg-info/not-zip-safe
django_file_repository.egg-info/top_level.txt
repository/__init__.py
repository/admin.py
repository/forms.py
repository/models.py
repository/tests.py
repository/urls.py
repository/views.py