Metadata-Version: 1.0
Name: django-file-repository
Version: 0.2b
Summary: Simple file repository with public/private files, tags and categories.
Home-page: http://github.com/cidadania/django-file-repository
Author: Oscar Carballal Prego
Author-email: oscar.carballal@cidadania.coop
License: GPLv3 license, see LICENSE
Platform: UNKNOWN
